query_builder/__init__.py
query_builder/__main__.py
query_builder/cli.py
query_builder/base_classes/__init__.py
query_builder/base_classes/base_mapper.py
query_builder/base_classes/base_service.py
query_builder/base_classes/base_use_case.py
query_builder/core/__init__.py
query_builder/core/filter_parser.py
query_builder/core/query_builder.py
query_builder/core/search_parser.py
query_builder/core/select_parser.py
query_builder/core/sort_parser.py
query_builder/examples/__init__.py
query_builder/examples/user_example.py
query_builder/exceptions/__init__.py
query_builder/exceptions/query_builder_exceptions.py
query_builder/tests/__init__.py
query_builder/tests/test_filter_parser.py
query_builder/utils/__init__.py
query_builder/utils/relationship_utils.py
fastapi_sqlalchemy_query_builder-1.0.1.dist-info/METADATA
fastapi_sqlalchemy_query_builder-1.0.1.dist-info/WHEEL
fastapi_sqlalchemy_query_builder-1.0.1.dist-info/entry_points.txt
fastapi_sqlalchemy_query_builder-1.0.1.dist-info/top_level.txt
fastapi_sqlalchemy_query_builder-1.0.1.dist-info/RECORD
