Metadata-Version: 2.4
Name: fastapi-sqlalchemy-query-builder
Version: 1.0.1
Summary: A library for building SQLAlchemy queries with support for advanced filtering, sorting, text search, field and relationship selection, pagination, and model to Pydantic schema mapping
Home-page: https://github.com/Pedroffda/fastapi-query-builder
Author: Pedro
Author-email: Pedro <pedro@example.com>
License: MIT
Project-URL: Homepage, https://github.com/Pedroffda/fastapi-query-builder
Project-URL: Repository, https://github.com/Pedroffda/fastapi-query-builder
Project-URL: Documentation, https://github.com/Pedroffda/fastapi-query-builder#readme
Project-URL: Bug Tracker, https://github.com/Pedroffda/fastapi-query-builder/issues
Classifier: Development Status :: 4 - Beta
Classifier: Intended Audience :: Developers
Classifier: License :: OSI Approved :: MIT License
Classifier: Programming Language :: Python :: 3
Classifier: Programming Language :: Python :: 3.8
Classifier: Programming Language :: Python :: 3.9
Classifier: Programming Language :: Python :: 3.10
Classifier: Programming Language :: Python :: 3.11
Classifier: Programming Language :: Python :: 3.12
Classifier: Topic :: Software Development :: Libraries :: Python Modules
Classifier: Topic :: Database
Classifier: Framework :: FastAPI
Requires-Python: >=3.8
Requires-Dist: sqlalchemy>=1.4.0
Requires-Dist: fastapi>=0.68.0
Requires-Dist: pydantic>=1.8.0
Requires-Dist: starlette>=0.14.0
Provides-Extra: dev
Requires-Dist: pytest>=6.0; extra == "dev"
Requires-Dist: pytest-asyncio>=0.18.0; extra == "dev"
Requires-Dist: black>=21.0; extra == "dev"
Requires-Dist: isort>=5.0; extra == "dev"
Requires-Dist: flake8>=3.8; extra == "dev"
Requires-Dist: mypy>=0.910; extra == "dev"
Dynamic: author
Dynamic: home-page
Dynamic: requires-python
